fake_plugin/__init__.py
fake_plugin/backends.txt
fake_plugin/config.py
fake_plugin/interface.py
fake_plugin/plugin.py
fake_plugin-0.0.1.dist-info/licenses/LICENSE
fake_plugin-0.0.1.dist-info/METADATA
fake_plugin-0.0.1.dist-info/WHEEL
fake_plugin-0.0.1.dist-info/top_level.txt
fake_plugin-0.0.1.dist-info/RECORD
